src/stack.v
module stack(
    input wire CLK,
    input wire reset,
    input wire push,
    input wire pop,
    output wire [9:0] stack_addr,
    output wire error 
);
    // Start bei BASE (0x07F), wächst Richtung 0
    localparam BASE = 10'h07F;
    reg [9:0] sp; 

    // LOGIK FÜR DIE RAM-ADRESSE:
    // Beim PUSH: Nutze aktuellen SP (da er auf das freie Feld zeigt).
    // Beim POP:  Nutze SP + 1 (da dort der letzte gültige Wert liegt).
    assign stack_addr = (pop) ? (sp + 10'd1) : sp;

    // Fehlerlogik:
    // Underflow: Wenn wir bei BASE sind und POP versuchen.
    // Overflow:  Wenn wir bei 0 sind und PUSH versuchen.
    assign error = (pop && sp == BASE) || (push && sp == 10'd0);

    always @(posedge CLK or posedge reset) begin
        if (reset) begin
            sp <= BASE; 
        end 
        else if (push && !error) begin
            // Erst wird der Wert an [sp] geschrieben (im RAM),
            // dann dekrementiert dieser Block den SP für den nächsten Befehl.
            sp <= sp - 10'd1;
        end 
        else if (pop && !error) begin
            // Der Wert wird von [sp+1] gelesen (siehe assign oben),
            // danach wird der SP hier wieder erhöht.
            sp <= sp + 10'd1;
        end
    end
endmodule

src/ram.v
module ram(
    input [9:0] Addr,
    input [15:0] WriteData,
    input WriteEnable,
    input ReadEnable,
    input CLK,
    output reg [15:0] ReadData
);

    reg [15:0] memory [0:1023];

    always @(*) begin
        if (ReadEnable) begin
            ReadData = memory[Addr];
        end
    end

    always @(posedge CLK) begin
        if (WriteEnable) begin
            memory[Addr] <= WriteData;
        end
    end

endmodule

src/alu.v
module alu(
    input wire CLK,
    input wire reset,
    input [15:0] A, 
    input [15:0] B,
    input [3:0] Mode,
    output reg [15:0] Result,
    output reg [1:0] FlagsOut    // Direkt als Reg für das interne Gedächtnis
);

    reg [1:0] next_flags;
    reg update_flags;

    always @(*) begin
        update_flags = 1'b1;     // Standardmäßig Flags aktualisieren
        Result = 16'b0;
        next_flags = FlagsOut;   // Standard: Flags behalten

        case(Mode)
            4'b0001: begin       // ADD // ADI
                {next_flags[1], Result} = A + B;
                next_flags[0] = (Result == 16'b0);
            end
            4'b0010: begin       // ADC
                {next_flags[1], Result} = A + B + FlagsOut[1];
                next_flags[0] = (Result == 16'b0);
            end
            4'b0011: begin       // SUB // SBI
                Result = A - B;
                next_flags[0] = (Result == 16'b0);
                next_flags[1] = (A < B);
            end
            4'b0100: begin       // SHR
                Result = A >> 1; 
                next_flags[0] = (Result == 16'b0);
                next_flags[1] = A[0];
            end
            4'b0101: begin       // AND
                Result = A & B;
                next_flags[0] = (Result == 16'b0);
                next_flags[1] = 1'b0;
            end
            4'b0110: begin       // IOR
                Result = A | B;
                next_flags[0] = (Result == 16'b0);
                next_flags[1] = 1'b0;
            end
            4'b0111: begin       // XOR
                Result = A ^ B;
                next_flags[0] = (Result == 16'b0);
                next_flags[1] = 1'b0;
            end
            4'b1000: begin       // NAND
                Result = ~(A & B);
                next_flags[0] = (Result == 16'b0);
                next_flags[1] = 1'b0;
            end
            4'b1001: begin       // NOR
                Result = ~(A | B);
                next_flags[0] = (Result == 16'b0);
                next_flags[1] = 1'b0;
            end
            4'b1010: begin       // XNOR
                Result = ~(A ^ B);
                next_flags[0] = (Result == 16'b0);
                next_flags[1] = 1'b0;
            end
            4'b1011: begin       // NOT
                Result = ~A;
                next_flags[0] = (Result == 16'b0);
                next_flags[1] = 1'b0;
            end
            4'b1100: begin       // CMP
                Result = 16'b0; 
                next_flags[0] = (A == B);
                next_flags[1] = (A < B);
            end
            default: begin
                Result = 16'b0;
                update_flags = 1'b0;
            end
        endcase
    end

    // --- Synchrones Speichern der Flags ---
    always @(posedge CLK or posedge reset) begin
        if (reset) begin
            FlagsOut <= 2'b0;
        end else if (update_flags) begin
            FlagsOut <= next_flags;
        end
    end

endmodule

src/regfile.v
module regfile(
    input wire [4:0] ReadRegAddr0,
    input wire [4:0] ReadRegAddr1,
    input wire [4:0] WriteRegAddr,
    input wire [15:0] WriteData,
    input wire RegWriteEn,
    input wire CLK,
    output reg [15:0] ReadData0,
    output reg [15:0] ReadData1
);

    // Speicher-Definitionen
    reg [15:0] Register [31:1];       // Register 1 bis 31

    // --- LESEN (Kombinatorisch) ---
    always @(*) begin
        // Standardwert für Register 0 (Hardwired Zero)
        ReadData0 = 16'b0;
        if (ReadRegAddr0 >= 1 && ReadRegAddr0 <= 31) ReadData0 = Register[ReadRegAddr0];

        ReadData1 = 16'b0;
        if (ReadRegAddr1 >= 1 && ReadRegAddr1 <= 31) ReadData1 = Register[ReadRegAddr1];  
    end

    // --- SCHREIBEN (Synchron) ---
    always @(posedge CLK) begin
        if (RegWriteEn) begin
            if (WriteRegAddr >= 1 && WriteRegAddr <= 31) Register[WriteRegAddr] <= WriteData;
        end
    end

endmodule

src/decoder.v
module decoder(
    input [5:0] opcode,
    input [1:0] Flags,

    output reg RegWrite,
    output reg MemRead,
    output reg MemWrite,
    output reg StackPush,
    output reg StackPop,
    output reg JmpInstruction,
    output reg CLK_HLT,
    output reg AtoA,
    output reg BtoB,
    output reg CtoC,
    output reg AtoC,
    output reg [3:0] AluMode
);



    always @(*) begin
        // Standardwerte
        RegWrite = 0;
        MemRead = 0;
        MemWrite = 0;
        StackPush = 0;
        StackPop = 0;
        JmpInstruction = 0;
        CLK_HLT = 0;
        AtoA = 0;
        BtoB = 0;
        CtoC = 0;
        AtoC = 0;
        AluMode = 4'b0000;
        case (opcode)
            6'b000000: begin // Beispiel: NOP
                // Keine Operation
            end
            6'b000001: begin // Beispiel: HLT
                // Halte den Prozessor
                CLK_HLT = 1;
            end
            6'b000010: begin // Beispiel: LOD
                MemRead = 1;
                RegWrite = 1;
                AtoC = 1;
            end
            6'b000011: begin // Beispiel: STO
                MemWrite = 1;
                AtoA = 1;
            end
            6'b000100: begin // Beispiel: LDR
                MemRead = 1;
                RegWrite = 1;
                AtoA = 1;
                CtoC = 1;
            end
            6'b000101: begin // Beispiel: STR
                MemWrite = 1;
                AtoA = 1;
                BtoB = 1;
            end
            6'b000110: begin // Beispiel: LDI
                RegWrite = 1;
                AtoC = 1;
            end
            6'b000111: begin // Beispiel: LBI
                RegWrite = 1;
            end
            6'b001000: begin // Beispiel: LPC
                RegWrite = 1;
                CtoC = 1;
            end
            6'b001001: begin // Beispiel: LSP
                RegWrite = 1;
                CtoC = 1;
            end
            6'b001010: begin // Beispiel: MOV
                RegWrite = 1;
                AtoA = 1;
                CtoC = 1;
            end
            6'b001011: begin // Beispiel: ADD
                AluMode = 4'b0001;
                RegWrite = 1;
                AtoA = 1;
                BtoB = 1;
                CtoC = 1;
            end
            6'b001100: begin // Beispiel: ADC
            AluMode = 4'b0010;
                RegWrite = 1;
                AtoA = 1;
                BtoB = 1;
                CtoC = 1;
            end
            6'b001101: begin // Beispiel: ADI
                AluMode = 4'b0001;
                RegWrite = 1;
                AtoA = 1;
                AtoC = 1;
            end
            6'b001110: begin // Beispiel: SUB
                AluMode = 4'b0011;
                RegWrite = 1;
                AtoA = 1;
                BtoB = 1;
                CtoC = 1;
            end
            6'b001111: begin // Beispiel: SBI
                AluMode = 4'b0011;
                RegWrite = 1;
                AtoA = 1;
                AtoC = 1;
            end
            6'b010000: begin // Beispiel: SHR
                AluMode = 4'b0100;
                RegWrite = 1;
                CtoC = 1;
            end
            6'b010001: begin // Beispiel: AND
                AluMode = 4'b0101;
                RegWrite = 1;
                AtoA = 1;
                BtoB = 1;
                CtoC = 1;
            end
            6'b010010: begin // Beispiel: IOR
                AluMode = 4'b0110;
                RegWrite = 1;
                AtoA = 1;
                BtoB = 1;
                CtoC = 1;
            end
            6'b010011: begin // Beispiel: XOR
                AluMode = 4'b0111;
                RegWrite = 1;
                AtoA = 1;
                BtoB = 1;
                CtoC = 1;
            end
            6'b010100: begin // Beispiel: NAN
                AluMode = 4'b1000;
                RegWrite = 1;
                AtoA = 1;
                BtoB = 1;
                CtoC = 1;
            end
            6'b010101: begin // Beispiel: NOR
                AluMode = 4'b1001;
                RegWrite = 1;
                AtoA = 1;
                BtoB = 1;
                CtoC = 1;
            end
            6'b010110: begin // Beispiel: XNO
                AluMode = 4'b1010;
                RegWrite = 1;
                AtoA = 1;
                BtoB = 1;
                CtoC = 1;
            end
            6'b010111: begin // Beispiel: NOT
                AluMode = 4'b1011;
                RegWrite = 1;
                AtoA = 1;
                CtoC = 1;
            end
            6'b011000: begin // Beispiel: CMP
                AluMode = 4'b1100;
                AtoA = 1;
                BtoB = 1;
            end
            6'b011001: begin // Beispiel: JMP
                JmpInstruction = 1;
            end
            6'b011010: begin // Beispiel: JMR
                JmpInstruction = 1;
                AtoA = 1;
            end
            6'b011011: begin // Beispiel: JEZ
                JmpInstruction = Flags[0];
            end
            6'b011100: begin // Beispiel: JNZ
                JmpInstruction = ~Flags[0];
            end
            6'b011101: begin // Beispiel: JEC
                JmpInstruction = Flags[1];
            end
            6'b011110: begin // Beispiel: JNC
                JmpInstruction = ~Flags[1];
            end
            6'b011111: begin // Beispiel: JEH
                JmpInstruction = ~(Flags[1] | Flags[0]);
            end
            6'b100000: begin // Beispiel: JNH
                JmpInstruction = (Flags[1] | Flags[0]);
            end
            6'b100001: begin // Beispiel: PSH
                MemWrite = 1;
                StackPush = 1;
                AtoA = 1;
            end
            6'b100010: begin // Beispiel: POP
                MemRead = 1;
                StackPop = 1;
                RegWrite = 1;
                CtoC = 1;
            end
            6'b100011: begin // Beispiel: CAL
                MemWrite = 1;
                StackPush = 1;
                JmpInstruction = 1;
            end
            6'b100100: begin // Beispiel: RET
                MemRead = 1;
                StackPop = 1;
                JmpInstruction = 1;
            end
            default: begin
                // Unbekannter Opcode, keine Aktion
            end
        endcase



    end

endmodule

src/instruction_memory.v
module instruction_memory(
    input [9:0] address,
    output wire [23:0] instruction
);

    reg [23:0] rom [0:1023];

    initial begin
        $readmemb("instruction_memory.bin", rom);

        // rom[0] = 24'b000110_00001_0000000000_000 ; // LDI R1, 0
        // rom[1] = 24'b000110_00010_0000000001_000 ; // LDI R2, 1
        // rom[2] = 24'b000110_00011_0011111010_000 ; // LDI R3, 250
        // rom[3] = 24'b001011_00001_00010_000_00001 ; // ADD R1, R1, R2
        // rom[4] = 24'b001011_00001_00010_000_00010 ; // ADD R2, R1, R2
        // rom[5] = 24'b011000_00001_00011_00000000 ; // CMP R1, R3
        // rom[6] = 24'b100000_00000_0000000011_000 ; // JEH 7
        // rom[7] = 24'b000001_000000000000000000 ; // HLT
    end

    assign instruction = rom[address];

endmodule

src/pc.v
module pc(
    input wire CLK,
    input wire Reset,
    input wire EnableIncrement,
    input wire EnableJump,
    input wire [9:0] JumpAddr,
    output reg [9:0] PCout    // output reg ist hier perfekt
);

    always @(posedge CLK or posedge Reset) begin
        if (Reset) begin
            PCout <= 10'b0;   // Zurück auf Anfang
        end 
        else if (EnableJump) begin
            PCout <= JumpAddr; // Springe zu einer Adresse
        end
        else if (EnableIncrement) begin
            PCout <= PCout + 1; // Normaler nächster Befehl
        end
    end

endmodule

src/clk_ctrl.v
module clk_ctrl(
    input wire clk_in,      // Der schnelle Hardware-Takt
    input wire reset,       // Reset um wieder zu starten
    input wire hlt_signal,  // Kommt vom Decoder (Opcode 000001)
    output wire clk_out     // Der Takt, der an PC, RAM und RegFile geht
);

    reg halted;

    always @(posedge clk_in or posedge reset) begin
        if (reset) begin
            halted <= 1'b0;
        end else if (hlt_signal) begin
            halted <= 1'b1;
        end
    end

    // Clock Gating: Nur wenn nicht 'halted', wird der Takt weitergegeben
    // Wir nutzen hier ein AND-Gatter Prinzip
    assign clk_out = clk_in & (~halted);

endmodule

src/cpu_top.v
`include "pc.v"
`include "instruction_memory.v"
`include "decoder.v"
`include "regfile.v"
`include "alu.v"
`include "ram.v"
`include "stack.v"
`include "clk_ctrl.v" // Vergiss nicht die Datei für den Clock-Controller

module cpu_top(
    input wire CLK,      // Dies ist der echte Hardware-Takt von außen
    input wire Reset,
    output wire CLK_HLT  // HLT Signal vom Decoder
);

    // --- Interne Clock ---
    wire internal_clk; 

    // --- Restliche Wires ---
    wire [23:0] instruction;
    wire [5:0] opcode = instruction[23:18];
    wire [9:0] PCout;
    wire [15:0] RegData0, RegData1, AluData, MemData;
    wire [1:0] FlagOut;
    wire [9:0] StackPointer;

    wire RegWriteEn, MemRead, MemWrite, StackPush, StackPop, JmpInstruction, AtoA, BtoB, CtoC, AtoC;
    wire [3:0] AluMode;

    // --- Clock Controller ---
    // Erzeugt aus dem äußeren CLK einen internal_clk, der bei HLT stoppt
    clk_ctrl system_clk (
        .clk_in(CLK),
        .reset(Reset),
        .hlt_signal(CLK_HLT),
        .clk_out(internal_clk)
    );

    // --- Jump Adress Logik ---
    wire [9:0] JmpAddr = (opcode == 6'b011010) ? RegData0[9:0] : 
                        (opcode == 6'b100100) ? MemData[9:0] : 
                        instruction[12:3];

    // --- Program Counter ---
    pc programm_counter (
        .CLK(internal_clk),
        .Reset(Reset),
        .EnableIncrement(~JmpInstruction),
        .EnableJump(JmpInstruction),
        .JumpAddr(JmpAddr),
        .PCout(PCout)
    );

    // --- Instruction Memory ---
    instruction_memory imem (
        .address(PCout),
        .instruction(instruction)
    );

    // --- Decoder ---
    decoder OPdecoder (
        .opcode(opcode),
        .Flags(FlagOut),
        .RegWrite(RegWriteEn),
        .MemRead(MemRead),
        .MemWrite(MemWrite),
        .StackPush(StackPush),
        .StackPop(StackPop),
        .JmpInstruction(JmpInstruction),
        .CLK_HLT(CLK_HLT),
        .AtoA(AtoA), .BtoB(BtoB), .CtoC(CtoC), .AtoC(AtoC),
        .AluMode(AluMode)
    );

    // --- Register Adress Multiplexer ---
    wire [4:0] ReadReg0 = (AtoA) ? instruction[17:13] : 5'b0;
    wire [4:0] ReadReg1 = (BtoB) ? instruction[12:8]  : 5'b0;
    wire [4:0] WriteReg = (CtoC) ? instruction[4:0]   : 
                          (AtoC) ? instruction[17:13] : 
                          (opcode == 6'b000111) ? 5'b11111 : // LBI
                          (opcode == 6'b010000) ? instruction[4:0] : // SHR
                          5'b0;

    // --- Register File ---
    wire [15:0] RegWriteData = (MemRead) ? MemData : 
                               (opcode == 6'b000110) ? {6'b0, instruction[12:3]} : // LDI
                               (opcode == 6'b000111) ? instruction[17:2] :  // LBI
                               (opcode == 6'b001001) ? {6'b0 , StackPointer} : // LSP
                                (opcode == 6'b001000) ? {6'b0 , PCout} : // LPC
                                opcode == 6'b001010 ? RegData0 : // MOV
                               AluData;

    regfile registerfile (
        .CLK(internal_clk),
        .RegWriteEn(RegWriteEn),
        .ReadRegAddr0(ReadReg0),
        .ReadRegAddr1(ReadReg1),
        .WriteRegAddr(WriteReg),
        .WriteData(RegWriteData),
        .ReadData0(RegData0),
        .ReadData1(RegData1)
    );

    // --- ALU ---
    wire [15:0] AluInB = (opcode == 6'b001101 || opcode == 6'b001111) ? {6'b0, instruction[12:3]} : RegData1;

    alu arithmetic_logic_unit (
        .CLK(internal_clk),
        .reset(Reset),
        .A(RegData0),
        .B(AluInB),
        .Mode(AluMode),
        .Result(AluData),
        .FlagsOut(FlagOut)
    );

    // --- RAM ---
    wire [9:0] MemAddr = (opcode == 6'b000010 || opcode == 6'b000011) ? instruction[12:3] :
                        (opcode == 6'b000100) ? RegData0[9:0] :
                        (opcode == 6'b000101) ? RegData1[9:0] :
                        (opcode == 6'b100001 || opcode == 6'b100010 || opcode == 6'b100011 || opcode == 6'b100100) ? StackPointer :
                        AluData[9:0];

    wire [15:0] MemWriteData = (opcode == 6'b100011) ? {6'b0, PCout + 10'b1} : RegData0;

    ram data_ram (
        .CLK(internal_clk),
        .Addr(MemAddr),
        .WriteData(MemWriteData),
        .WriteEnable(MemWrite),
        .ReadEnable(MemRead),
        .ReadData(MemData)
    );

    // --- Stack ---
    stack ram_stack (
        .CLK(internal_clk),
        .reset(Reset),
        .push(StackPush),
        .pop(StackPop),
        .stack_addr(StackPointer),
        .error() 
    );

endmodule

src/cpu_tb.v
`timescale 1ns / 1ps

module cpu_tb();
    reg clk;
    reg reset;
    wire hlt;

    // Hilfsvariable für die Schleife
    integer i;

    // Deine CPU einbinden
    cpu_top uut (
        .CLK(clk),
        .Reset(reset),
        .CLK_HLT(hlt)
    );

    // Takt-Generator: Alle 5ns wechselt der Status (100 MHz)
    always #5 clk = ~clk;

    initial begin
        $display("Simulation startet...");
        clk = 0;
        reset = 1;      // Reset aktivieren
        #20 reset = 0;  // Nach 20ns Reset lösen
        
        // Warten bis die CPU den HLT-Befehl erreicht
        wait(hlt); 
        #10; // Kurz warten, damit der letzte Schreibvorgang sicher im Registerfile landet
        
        $display("\n--- REGISTER WERTE (R1 bis R31) ---");
        // Schleife von 1 bis 31
        for (i = 1; i <= 31; i = i + 1) begin
            // Zugriff auf das Register-Array in deiner regfile-Instanz innerhalb von uut
            $display("Register R%0d: %d", i, uut.registerfile.Register[i]);
        end
        $display("-----------------------------------\n");

        $display("HLT-Befehl erkannt. Test beendet.");
        $finish;
    end

    // Diese Zeilen erzeugen eine Datei für den Waveform-Viewer (z.B. GTKWave)
    initial begin
        $dumpfile("cpu_waves.vcd");
        $dumpvars(0, cpu_tb);
    end
endmodule

src/cpu_waves.vcd
$date
	Mon Jan 12 19:55:58 2026
$end
$version
	Icarus Verilog
$end
$timescale
	1ps
$end
$scope module cpu_tb $end
$var wire 1 ! hlt $end
$var reg 1 " clk $end
$var reg 1 # reset $end
$var integer 32 $ i [31:0] $end
$scope module uut $end
$var wire 1 " CLK $end
$var wire 1 # Reset $end
$var wire 6 % opcode [5:0] $end
$var wire 1 & internal_clk $end
$var wire 24 ' instruction [23:0] $end
$var wire 5 ( WriteReg [4:0] $end
$var wire 1 ) StackPush $end
$var wire 1 * StackPop $end
$var wire 10 + StackPointer [9:0] $end
$var wire 1 , RegWriteEn $end
$var wire 16 - RegWriteData [15:0] $end
$var wire 16 . RegData1 [15:0] $end
$var wire 16 / RegData0 [15:0] $end
$var wire 5 0 ReadReg1 [4:0] $end
$var wire 5 1 ReadReg0 [4:0] $end
$var wire 10 2 PCout [9:0] $end
$var wire 16 3 MemWriteData [15:0] $end
$var wire 1 4 MemWrite $end
$var wire 1 5 MemRead $end
$var wire 16 6 MemData [15:0] $end
$var wire 10 7 MemAddr [9:0] $end
$var wire 1 8 JmpInstruction $end
$var wire 10 9 JmpAddr [9:0] $end
$var wire 2 : FlagOut [1:0] $end
$var wire 1 ; CtoC $end
$var wire 1 ! CLK_HLT $end
$var wire 1 < BtoB $end
$var wire 1 = AtoC $end
$var wire 1 > AtoA $end
$var wire 4 ? AluMode [3:0] $end
$var wire 16 @ AluInB [15:0] $end
$var wire 16 A AluData [15:0] $end
$scope module OPdecoder $end
$var wire 6 B opcode [5:0] $end
$var wire 2 C Flags [1:0] $end
$var reg 4 D AluMode [3:0] $end
$var reg 1 > AtoA $end
$var reg 1 = AtoC $end
$var reg 1 < BtoB $end
$var reg 1 ! CLK_HLT $end
$var reg 1 ; CtoC $end
$var reg 1 8 JmpInstruction $end
$var reg 1 5 MemRead $end
$var reg 1 4 MemWrite $end
$var reg 1 , RegWrite $end
$var reg 1 * StackPop $end
$var reg 1 ) StackPush $end
$upscope $end
$scope module arithmetic_logic_unit $end
$var wire 16 E B [15:0] $end
$var wire 4 F Mode [3:0] $end
$var wire 1 # reset $end
$var wire 1 & CLK $end
$var wire 16 G A [15:0] $end
$var reg 2 H FlagsOut [1:0] $end
$var reg 16 I Result [15:0] $end
$var reg 2 J next_flags [1:0] $end
$var reg 1 K update_flags $end
$upscope $end
$scope module data_ram $end
$var wire 10 L Addr [9:0] $end
$var wire 1 5 ReadEnable $end
$var wire 16 M WriteData [15:0] $end
$var wire 1 4 WriteEnable $end
$var wire 1 & CLK $end
$var reg 16 N ReadData [15:0] $end
$upscope $end
$scope module imem $end
$var wire 24 O instruction [23:0] $end
$var wire 10 P address [9:0] $end
$upscope $end
$scope module programm_counter $end
$var wire 1 Q EnableIncrement $end
$var wire 1 8 EnableJump $end
$var wire 10 R JumpAddr [9:0] $end
$var wire 1 # Reset $end
$var wire 1 & CLK $end
$var reg 10 S PCout [9:0] $end
$upscope $end
$scope module ram_stack $end
$var wire 1 T error $end
$var wire 1 * pop $end
$var wire 1 ) push $end
$var wire 1 # reset $end
$var wire 10 U stack_addr [9:0] $end
$var wire 1 & CLK $end
$var parameter 10 V BASE $end
$var reg 10 W sp [9:0] $end
$upscope $end
$scope module registerfile $end
$var wire 5 X ReadRegAddr0 [4:0] $end
$var wire 5 Y ReadRegAddr1 [4:0] $end
$var wire 1 , RegWriteEn $end
$var wire 16 Z WriteData [15:0] $end
$var wire 5 [ WriteRegAddr [4:0] $end
$var wire 1 & CLK $end
$var reg 16 \ ReadData0 [15:0] $end
$var reg 16 ] ReadData1 [15:0] $end
$upscope $end
$scope module system_clk $end
$var wire 1 " clk_in $end
$var wire 1 & clk_out $end
$var wire 1 ! hlt_signal $end
$var wire 1 # reset $end
$var reg 1 ^ halted $end
$upscope $end
$upscope $end
$upscope $end
$enddefinitions $end
$comment Show the parameter values. $end
$dumpall
b1111111 V
$end
#0
$dumpvars
0^
b0 ]
b0 \
b1 [
b1100100 Z
b0 Y
b0 X
b1111111 W
b1111111 U
0T
b0 S
b1100100 R
1Q
b0 P
b110000010001100100000 O
bx N
b0 M
b0 L
0K
b0 J
b0 I
b0 H
b0 G
b0 F
b0 E
b0 D
b0 C
b110 B
b0 A
b0 @
b0 ?
0>
1=
0<
0;
b0 :
b1100100 9
08
b0 7
bx 6
05
04
b0 3
b0 2
b0 1
b0 0
b0 /
b0 .
b1100100 -
1,
b1111111 +
0*
0)
b1 (
b110000010001100100000 '
0&
b110 %
bx $
1#
0"
0!
$end
#5000
1&
1"
#10000
0&
0"
#15000
1&
1"
#20000
0&
0"
0#
#25000
b11001000 -
b11001000 Z
b10 (
b10 [
b11001000 9
b11001000 R
b110000100011001000000 '
b110000100011001000000 O
b1 2
b1 P
b1 S
1&
1"
#30000
0&
0"
#35000
b100101100 -
b100101100 Z
b11 (
b11 [
b100101100 9
b100101100 R
b110000110100101100000 '
b110000110100101100000 O
b10 2
b10 P
b10 S
1&
1"
#40000
0&
0"
#45000
b10010000 -
b10010000 Z
b100 (
b100 [
b10010000 9
b10010000 R
b110001000010010000000 '
b110001000010010000000 O
b11 2
b11 P
b11 S
1&
1"
#50000
0&
0"
#55000
b1111111 7
b1111111 L
b10010000 3
b10010000 M
0K
b10010000 /
b10010000 G
b10010000 \
b0 (
b0 [
b0 9
b0 R
b0 -
b0 Z
b100 1
b100 X
1>
1)
14
0=
0,
b100001 %
b100001 B
b100001001000000000000000 '
b100001001000000000000000 O
b100 2
b100 P
b100 S
1&
1"
#60000
0&
0"
#65000
b0 7
b0 L
b0 3
b0 M
0K
b100 (
b100 [
b0 /
b0 G
b0 \
b110010000 9
b110010000 R
b110010000 -
b110010000 Z
b0 1
b0 X
1=
1,
0>
0)
04
b1111110 +
b1111110 U
b110 %
b110 B
b1111110 W
b110001000110010000000 '
b110001000110010000000 O
b101 2
b101 P
b101 S
1&
1"
#70000
0&
0"
#75000
b1111110 7
b1111110 L
b0 (
b0 [
b10000 9
b10000 R
b0 -
b0 Z
0Q
b111 3
b111 M
18
1)
14
0=
0,
b100011 %
b100011 B
b100011000000000010000000 '
b100011000000000010000000 O
b110 2
b110 P
b110 S
1&
1"
#80000
0&
0"
#85000
b1111101 7
b1111101 L
0K
b1100100 /
b1100100 G
b1100100 \
b0 9
b0 R
b1 1
b1 X
1Q
1>
08
1)
14
b1111101 +
b1111101 U
b100001 %
b100001 B
b1100100 3
b1100100 M
b1111101 W
b100001000010000000000000 '
b100001000010000000000000 O
b10000 2
b10000 P
b10000 S
1&
1"
#90000
0&
0"
#95000
b1111100 -
b1111100 Z
b0 7
b0 L
b0 3
b0 M
0K
b0 /
b0 G
b0 \
b1 (
b1 [
b0 1
b0 X
1;
1,
0>
0)
04
b1001 %
b1001 B
b1111100 +
b1111100 U
b1001000000000000000001 '
b1001000000000000000001 O
b10001 2
b10001 P
b10001 S
b1111100 W
1&
1"
#100000
0&
0"
#105000
b1111111 7
b1111111 L
b1111111 -
b1111111 Z
b1111100 3
b1111100 M
b1111111 A
b1111111 I
b1111100 /
b1111100 G
b1111100 \
b11 9
b11 R
b11 @
b11 E
b1 1
b1 X
b0 J
1K
b1 (
b1 [
1=
1>
b1 ?
b1 D
b1 F
0;
1,
b1101 %
b1101 B
b1101000010000000011000 '
b1101000010000000011000 O
b10010 2
b10010 P
b10010 S
1&
1"
#110000
0&
0"
#115000
b0 9
b0 R
b10010000 6
b10010000 N
b10010000 -
b10010000 Z
0K
b0 @
b0 E
1;
15
b0 ?
b0 D
b0 F
0=
1>
1,
b1111111 3
b1111111 M
b0 A
b0 I
b100 %
b100 B
b1111111 /
b1111111 G
b1111111 \
b100000010000000000001 '
b100000010000000000001 O
b10011 2
b10011 P
b10011 S
1&
1"
#120000
0&
0"
#125000
b10010000 @
b10010000 E
b10010000 .
b10010000 ]
b100000 9
b100000 R
b10010000 7
b10010000 L
b1 0
b1 Y
b0 -
b0 Z
b0 (
b0 [
b11111 1
b11111 X
1<
14
0;
1>
05
0,
bx 3
bx M
0K
b101 %
b101 B
bx /
bx G
bx \
b101111110000100000000 '
b101111110000100000000 O
b10100 2
b10100 P
b10100 S
1&
1"
#130000
0&
0"
#135000
b10010001 -
b10010001 Z
b10010000 3
b10010000 M
b10010001 7
b10010001 L
b1 (
b1 [
b0 .
b0 ]
b10010000 /
b10010000 G
b10010000 \
b1 9
b1 R
b1 @
b1 E
b0 J
b10010001 A
b10010001 I
1K
b0 0
b0 Y
b1 1
b1 X
1=
1,
b1 ?
b1 D
b1 F
0<
1>
04
b1101 %
b1101 B
b1101000010000000001000 '
b1101000010000000001000 O
b10101 2
b10101 P
b10101 S
1&
1"
#140000
0&
0"
#145000
b0 -
b0 Z
b10010001 7
b10010001 L
b0 (
b0 [
b10010001 .
b10010001 ]
b100000 9
b100000 R
b1 0
b1 Y
0K
b10010001 @
b10010001 E
b11110 1
b11110 X
1<
14
b0 ?
b0 D
b0 F
0=
1>
0,
bx 3
bx M
b0 A
b0 I
b101 %
b101 B
bx /
bx G
bx \
b101111100000100000000 '
b101111100000100000000 O
b10110 2
b10110 P
b10110 S
1&
1"
#150000
0&
0"
#155000
b10010010 -
b10010010 Z
b10010001 3
b10010001 M
b10010010 7
b10010010 L
b1 (
b1 [
b0 .
b0 ]
b10010001 /
b10010001 G
b10010001 \
b1 9
b1 R
b1 @
b1 E
b0 J
b10010010 A
b10010010 I
1K
b0 0
b0 Y
b1 1
b1 X
1=
1,
b1 ?
b1 D
b1 F
0<
1>
04
b1101 %
b1101 B
b1101000010000000001000 '
b1101000010000000001000 O
b10111 2
b10111 P
b10111 S
1&
1"
#160000
0&
0"
#165000
b0 -
b0 Z
b10010010 7
b10010010 L
b0 (
b0 [
b10010010 .
b10010010 ]
b100000 9
b100000 R
b1 0
b1 Y
0K
b10010010 @
b10010010 E
b11101 1
b11101 X
1<
14
b0 ?
b0 D
b0 F
0=
1>
0,
bx 3
bx M
b0 A
b0 I
b101 %
b101 B
bx /
bx G
bx \
b101111010000100000000 '
b101111010000100000000 O
b11000 2
b11000 P
b11000 S
1&
1"
#170000
0&
0"
#175000
b10010011 -
b10010011 Z
b10010010 3
b10010010 M
b10010011 7
b10010011 L
b1 (
b1 [
b0 .
b0 ]
b10010010 /
b10010010 G
b10010010 \
b1 9
b1 R
b1 @
b1 E
b0 J
b10010011 A
b10010011 I
1K
b0 0
b0 Y
b1 1
b1 X
1=
1,
b1 ?
b1 D
b1 F
0<
1>
04
b1101 %
b1101 B
b1101000010000000001000 '
b1101000010000000001000 O
b11001 2
b11001 P
b11001 S
1&
1"
#180000
0&
0"
#185000
b0 -
b0 Z
b10010011 7
b10010011 L
b0 (
b0 [
b10010011 .
b10010011 ]
b100000 9
b100000 R
b1 0
b1 Y
0K
b10010011 @
b10010011 E
b11100 1
b11100 X
1<
14
b0 ?
b0 D
b0 F
0=
1>
0,
bx 3
bx M
b0 A
b0 I
b101 %
b101 B
bx /
bx G
bx \
b101111000000100000000 '
b101111000000100000000 O
b11010 2
b11010 P
b11010 S
1&
1"
#190000
0&
0"
#195000
b10010100 -
b10010100 Z
b10010011 3
b10010011 M
b10010100 7
b10010100 L
b1 (
b1 [
b0 .
b0 ]
b10010011 /
b10010011 G
b10010011 \
b1 9
b1 R
b1 @
b1 E
b0 J
b10010100 A
b10010100 I
1K
b0 0
b0 Y
b1 1
b1 X
1=
1,
b1 ?
b1 D
b1 F
0<
1>
04
b1101 %
b1101 B
b1101000010000000001000 '
b1101000010000000001000 O
b11011 2
b11011 P
b11011 S
1&
1"
#200000
0&
0"
#205000
b0 -
b0 Z
b10010100 7
b10010100 L
b0 (
b0 [
b10010100 .
b10010100 ]
b100000 9
b100000 R
b1 0
b1 Y
0K
b10010100 @
b10010100 E
b11011 1
b11011 X
1<
14
b0 ?
b0 D
b0 F
0=
1>
0,
bx 3
bx M
b0 A
b0 I
b101 %
b101 B
bx /
bx G
bx \
b101110110000100000000 '
b101110110000100000000 O
b11100 2
b11100 P
b11100 S
1&
1"
#210000
0&
0"
#215000
b10010101 -
b10010101 Z
b10010100 3
b10010100 M
b10010101 7
b10010101 L
b1 (
b1 [
b0 .
b0 ]
b10010100 /
b10010100 G
b10010100 \
b1 9
b1 R
b1 @
b1 E
b0 J
b10010101 A
b10010101 I
1K
b0 0
b0 Y
b1 1
b1 X
1=
1,
b1 ?
b1 D
b1 F
0<
1>
04
b1101 %
b1101 B
b1101000010000000001000 '
b1101000010000000001000 O
b11101 2
b11101 P
b11101 S
1&
1"
#220000
0&
0"
